splurge_tools/__init__.py
splurge_tools/base58.py
splurge_tools/case_helper.py
splurge_tools/common_utils.py
splurge_tools/data_transformer.py
splurge_tools/data_validator.py
splurge_tools/decorators.py
splurge_tools/dsv_helper.py
splurge_tools/exceptions.py
splurge_tools/factory.py
splurge_tools/path_validator.py
splurge_tools/protocols.py
splurge_tools/py.typed
splurge_tools/random_helper.py
splurge_tools/resource_manager.py
splurge_tools/streaming_tabular_data_model.py
splurge_tools/string_tokenizer.py
splurge_tools/tabular_data_model.py
splurge_tools/tabular_utils.py
splurge_tools/text_file_helper.py
splurge_tools/text_normalizer.py
splurge_tools/type_helper.py
splurge_tools/typed_tabular_data_model.py
splurge_tools-2025.5.1.dist-info/licenses/LICENSE
splurge_tools-2025.5.1.dist-info/METADATA
splurge_tools-2025.5.1.dist-info/WHEEL
splurge_tools-2025.5.1.dist-info/top_level.txt
splurge_tools-2025.5.1.dist-info/RECORD
